pitchtools/__init__.py
pitchtools/py.typed
pitchtools/vectorized.py
pitchtools-1.16.1.dist-info/METADATA
pitchtools-1.16.1.dist-info/WHEEL
pitchtools-1.16.1.dist-info/top_level.txt
pitchtools-1.16.1.dist-info/RECORD
