Metadata-Version: 2.4
Name: pitchtools
Version: 1.16.1
Summary: Utilities to work with pitches, convert between midinotes, frequency and notenames
Author-email: Eduardo Moguillansky <eduardo.moguillansky@gmail.com>
Project-URL: Homepage, https://github.com/gesellkammer/pitchtools
Classifier: Programming Language :: Python :: 3
Classifier: Operating System :: OS Independent
Requires-Python: >=3.9
